{
	"name": "hexparse.book.entry",
	"category": "hexcasting:patterns",
	"icon": "minecraft:command_block",
	"pages": [
		{
			"type": "hexcasting:pattern",
			"op_id": "hexparse:focus2code",
			"anchor": "hexparse:focus2code",
			"input": "",
			"output": "",
			"text": "book.descrip.hexparse:focus2code"
		},
		{
			"type": "hexcasting:pattern",
			"op_id": "hexparse:remove_comments",
			"anchor": "hexparse:remove_comments",
			"input": "list",
			"output": "list",
			"text": "book.descrip.hexparse:remove_comments"
		}
	]
}